{
  "project_info": {
    "project_number": "838559461497",
    "project_id": "meldep",
    "storage_bucket": "meldep.firebasestorage.app"
  },
  "client": [
    {
      "client_info": {
        "mobilesdk_app_id": "1:838559461497:android:0be8e1d76f17d7830aa4a8",
        "android_client_info": {
          "package_name": "com.example.test_project"
        }
      },
      "oauth_client": [],
      "api_key": [
        {
          "current_key": "AIzaSyDfHzup1I7LOFHD-dDaoKkG97N8sB4d_mw"
        }
      ],
      "services": {
        "appinvite_service": {
          "other_platform_oauth_client": []
        }
      }
    }
  ],
  "configuration_version": "1"
}